pixelarraythirdparty/__init__.py
pixelarraythirdparty/client.py
pixelarraythirdparty/cron/__init__.py
pixelarraythirdparty/cron/cron.py
pixelarraythirdparty/feedback/__init__.py
pixelarraythirdparty/feedback/feedback.py
pixelarraythirdparty/order/__init__.py
pixelarraythirdparty/order/order.py
pixelarraythirdparty/product/__init__.py
pixelarraythirdparty/product/product.py
pixelarraythirdparty/project/__init__.py
pixelarraythirdparty/project/project.py
pixelarraythirdparty/unified_login/__init__.py
pixelarraythirdparty/unified_login/unified_login.py
pixelarraythirdparty/user/__init__.py
pixelarraythirdparty/user/user.py
pixelarraythirdparty-1.2.4.dist-info/licenses/LICENSE
pixelarraythirdparty-1.2.4.dist-info/METADATA
pixelarraythirdparty-1.2.4.dist-info/WHEEL
pixelarraythirdparty-1.2.4.dist-info/top_level.txt
pixelarraythirdparty-1.2.4.dist-info/RECORD
